pagos_data_cipher/__init__.py
pagos_data_cipher/cipher.py
askparrot_decryption_sdk-0.2.3.dist-info/METADATA
askparrot_decryption_sdk-0.2.3.dist-info/WHEEL
askparrot_decryption_sdk-0.2.3.dist-info/top_level.txt
askparrot_decryption_sdk-0.2.3.dist-info/RECORD
